myfacerec/__init__.py
myfacerec/cli.py
myfacerec/combined_model.py
myfacerec/config.py
myfacerec/data_store.py
myfacerec/detectors.py
myfacerec/embedders.py
myfacerec/facial_recognition.py
myfacerec/hooks.py
myfacerec/setup.py
myfacerec/plugins/__init__.py
myfacerec/plugins/base.py
myfacerec/plugins/sample_plugin.py
rolo_rec-0.4.9.dist-info/METADATA
rolo_rec-0.4.9.dist-info/WHEEL
rolo_rec-0.4.9.dist-info/entry_points.txt
rolo_rec-0.4.9.dist-info/top_level.txt
rolo_rec-0.4.9.dist-info/RECORD
